gitlab_downloader/__init__.py
gitlab_downloader/main.py
test/__init__.py
test/test_gitlab_downloader.py
gitlab_projects_downloader-1.0.2.dist-info/LICENSE
gitlab_projects_downloader-1.0.2.dist-info/METADATA
gitlab_projects_downloader-1.0.2.dist-info/WHEEL
gitlab_projects_downloader-1.0.2.dist-info/entry_points.txt
gitlab_projects_downloader-1.0.2.dist-info/top_level.txt
gitlab_projects_downloader-1.0.2.dist-info/RECORD
