Metadata-Version: 2.1
Name: gitlab_projects_downloader
Version: 1.0.2
Summary: A simple service for downloading your projects from GitLab in tgz format
Home-page: https://github.com/AlbertoBarrago/gitlab_projects_exporter
Author: alBz
Author-email: alberto.barrago@gmail.com
Classifier: Programming Language :: Python :: 3
Classifier: License :: OSI Approved :: MIT License
Classifier: Operating System :: OS Independent
Classifier: Topic :: Software Development :: Libraries
Requires-Python: >=3.7
License-File: LICENSE
Requires-Dist: requests
Requires-Dist: python-dotenv
Requires-Dist: pylint
Requires-Dist: astroid
Requires-Dist: certifi
Requires-Dist: charset-normalizer
Requires-Dist: dill
Requires-Dist: isort
Requires-Dist: mccabe
Requires-Dist: tomlkit
Requires-Dist: urllib3
